setup.cfg
setup.py
googl/__init__.py
python_googl.egg-info/PKG-INFO
python_googl.egg-info/SOURCES.txt
python_googl.egg-info/dependency_links.txt
python_googl.egg-info/not-zip-safe
python_googl.egg-info/requires.txt
python_googl.egg-info/top_level.txt