Metadata-Version: 1.0
Name: python-googl
Version: 0.1
Summary: Python goo.gl url shortener wrapper
Home-page: http://code.google.com/p/python-googl
Author: Vince Spicer
Author-email: vinces1979@gmail.com
License: UNKNOWN
Keywords: google,url,googl
Platform: UNKNOWN
Classifier: Development Status :: 4 - Beta
Classifier: Operating System :: OS Independent
Classifier: Programming Language :: Python
Classifier: Topic :: Software Development :: Libraries :: Python Modules
